dataplicity_websocket_client-0.41.0.data/scripts/wsdump.py
dataplicity_websocket_client-0.41.0.dist-info/DESCRIPTION.rst
dataplicity_websocket_client-0.41.0.dist-info/METADATA
dataplicity_websocket_client-0.41.0.dist-info/RECORD
dataplicity_websocket_client-0.41.0.dist-info/WHEEL
dataplicity_websocket_client-0.41.0.dist-info/metadata.json
dataplicity_websocket_client-0.41.0.dist-info/top_level.txt
websocket/__init__.py
websocket/_abnf.py
websocket/_app.py
websocket/_core.py
websocket/_exceptions.py
websocket/_handshake.py
websocket/_http.py
websocket/_logging.py
websocket/_socket.py
websocket/_ssl_compat.py
websocket/_url.py
websocket/_utils.py
websocket/cacert.pem
websocket/tests/__init__.py
websocket/tests/test_websocket.py
websocket/tests/data/header01.txt
websocket/tests/data/header02.txt
