Metadata-Version: 2.0
Name: dataplicity-websocket-client
Version: 0.41.0
Summary: WebSocket client for python. hybi13 is supported.
Home-page: https://github.com/websocket-client/websocket-client.git
Author: Will McGugan
Author-email: will.mcgugan@wildfoundry.com
License: LGPL
Keywords: websockets
Platform: UNKNOWN
Classifier: Development Status :: 4 - Beta
Classifier: License :: OSI Approved :: GNU Library or Lesser General Public License (LGPL)
Classifier: Programming Language :: Python
Classifier: Programming Language :: Python :: 2
Classifier: Programming Language :: Python :: 3
Classifier: Operating System :: MacOS :: MacOS X
Classifier: Operating System :: POSIX
Classifier: Operating System :: Microsoft :: Windows
Classifier: Topic :: Internet
Classifier: Topic :: Software Development :: Libraries :: Python Modules
Classifier: Intended Audience :: Developers
Requires-Dist: six
